.travis.yml
CHANGES.txt
COPYRIGHT.txt
LICENSE.txt
MANIFEST.in
README.txt
bootstrap.py
buildout.cfg
setup.py
src/zc/__init__.py
src/zc.configuration.egg-info/PKG-INFO
src/zc.configuration.egg-info/SOURCES.txt
src/zc.configuration.egg-info/dependency_links.txt
src/zc.configuration.egg-info/namespace_packages.txt
src/zc.configuration.egg-info/not-zip-safe
src/zc.configuration.egg-info/requires.txt
src/zc.configuration.egg-info/top_level.txt
src/zc/configuration/README.txt
src/zc/configuration/__init__.py
src/zc/configuration/meta.zcml
src/zc/configuration/tests.py
src/zc/configuration/zcml.py
src/zc/configuration/demo/__init__.py
src/zc/configuration/demo/configure.zcml
src/zc/configuration/demo/spam.zcml
src/zc/configuration/demo/sub/__init__.py
src/zc/configuration/demo/sub/configure.zcml