Metadata-Version: 1.0
Name: zc.configuration
Version: 1.2.0
Summary: Extensions to zope.configuration
Home-page: UNKNOWN
Author: UNKNOWN
Author-email: UNKNOWN
License: ZPL 1.1
Platform: UNKNOWN
